noesium/agents/askura_agent/__init__.py
noesium/agents/askura_agent/askura_agent.py
noesium/agents/askura_agent/conversation.py
noesium/agents/askura_agent/extractor.py
noesium/agents/askura_agent/memory.py
noesium/agents/askura_agent/models.py
noesium/agents/askura_agent/prompts.py
noesium/agents/askura_agent/reflection.py
noesium/agents/askura_agent/summarizer.py
noesium/agents/askura_agent/utils.py
noesium/agents/deep_research/__init__.py
noesium/agents/deep_research/agent.py
noesium/agents/deep_research/prompts.py
noesium/agents/deep_research/schemas.py
noesium/agents/deep_research/state.py
noesium/agents/search/__init__.py
noesium/agents/search/agent.py
noesium/agents/search/state.py
noesium/core/__init__.py
noesium/core/consts.py
noesium/core/py.typed
noesium/core/agent/__init__.py
noesium/core/agent/base.py
noesium/core/goalith/errors.py
noesium/core/goalith/service.py
noesium/core/goalith/conflict/conflict.py
noesium/core/goalith/conflict/detector.py
noesium/core/goalith/decomposer/__init__.py
noesium/core/goalith/decomposer/base.py
noesium/core/goalith/decomposer/callable_decomposer.py
noesium/core/goalith/decomposer/llm_decomposer.py
noesium/core/goalith/decomposer/prompts.py
noesium/core/goalith/decomposer/simple_decomposer.py
noesium/core/goalith/goalgraph/graph.py
noesium/core/goalith/goalgraph/node.py
noesium/core/goalith/replanner/base.py
noesium/core/goalith/replanner/replanner.py
noesium/core/llm/__init__.py
noesium/core/llm/base.py
noesium/core/llm/litellm.py
noesium/core/llm/llamacpp.py
noesium/core/llm/message.py
noesium/core/llm/ollama.py
noesium/core/llm/openai.py
noesium/core/llm/openrouter.py
noesium/core/llm/prompt.py
noesium/core/memory/__init__.py
noesium/core/memory/base.py
noesium/core/memory/models.py
noesium/core/memory/memu/__init__.py
noesium/core/memory/memu/llm_adapter.py
noesium/core/memory/memu/memory_store.py
noesium/core/memory/memu/config/__init__.py
noesium/core/memory/memu/config/markdown_config.py
noesium-0.2.0.dist-info/licenses/LICENSE
noesium-0.2.0.dist-info/METADATA
noesium-0.2.0.dist-info/WHEEL
noesium-0.2.0.dist-info/top_level.txt
noesium-0.2.0.dist-info/RECORD
