Metadata-Version: 2.4
Name: noesium
Version: 0.2.0
Summary: Towards a cognitive agentic framework
Author-email: Xiaming Chen <chenxm35@gmail.com>
Maintainer-email: Xiaming Chen <chenxm35@gmail.com>
License-Expression: MIT
Project-URL: Homepage, https://github.com/mirasoth/noesium
Project-URL: Repository, https://github.com/mirasoth/noesium
Keywords: agents,multi-agent system,cognition,artificial intelligence
Classifier: Development Status :: 4 - Beta
Classifier: Intended Audience :: Developers
Classifier: Operating System :: OS Independent
Classifier: Programming Language :: Python :: 3
Classifier: Programming Language :: Python :: 3.11
Classifier: Programming Language :: Python :: 3.12
Classifier: Topic :: Software Development :: Libraries :: Python Modules
Requires-Python: >=3.11
License-File: LICENSE
Requires-Dist: pydantic>=2.0.0
Requires-Dist: requests>=2.31.0
Requires-Dist: httpx>=0.28.1
Requires-Dist: aiohttp>=3.12.15
Requires-Dist: aiofiles>=24.1.0
Requires-Dist: anyio>=4.9.0
Requires-Dist: python-dotenv>=1.1.1
Requires-Dist: colorlog>=6.8.0
Requires-Dist: typing-extensions>=4.8.0
Requires-Dist: deprecated>=1.2.18
Requires-Dist: psutil>=7.0.0
Requires-Dist: networkx>=3.5
Requires-Dist: bubus>=1.5.6
Provides-Extra: openai
Requires-Dist: openai>=1.0.0; extra == "openai"
Requires-Dist: instructor>=1.10.0; extra == "openai"
Provides-Extra: google
Requires-Dist: google-genai>=1.5.0; extra == "google"
Requires-Dist: google-api-python-client>=2.174.0; extra == "google"
Requires-Dist: google-auth-oauthlib>=1.2.2; extra == "google"
Requires-Dist: google-auth>=2.40.3; extra == "google"
Provides-Extra: aliyun
Requires-Dist: aliyun-python-sdk-core<3.0.0,>=2.13.1; extra == "aliyun"
Provides-Extra: litellm
Requires-Dist: litellm>=1.0.0; extra == "litellm"
Provides-Extra: local-llm
Requires-Dist: ollama>=0.5.3; extra == "local-llm"
Requires-Dist: llama-cpp-python>=0.3.16; extra == "local-llm"
Requires-Dist: huggingface-hub>=0.34.4; extra == "local-llm"
Provides-Extra: langchain
Requires-Dist: langchain-core>=0.3.72; extra == "langchain"
Requires-Dist: langchain-text-splitters>=0.3.0; extra == "langchain"
Requires-Dist: langchain-ollama>=0.2.0; extra == "langchain"
Requires-Dist: langgraph>=0.5.4; extra == "langchain"
Provides-Extra: postgres
Requires-Dist: psycopg2-binary>=2.9.0; extra == "postgres"
Requires-Dist: psycopg2>=2.9.10; extra == "postgres"
Provides-Extra: weaviate
Requires-Dist: weaviate-client<5,>=4; extra == "weaviate"
Requires-Dist: protobuf<6,>=5; extra == "weaviate"
Provides-Extra: datascience
Requires-Dist: matplotlib>=3.8.0; extra == "datascience"
Requires-Dist: pexpect>=4.9.0; extra == "datascience"
Requires-Dist: ipython>=8.18.0; extra == "datascience"
Requires-Dist: pandas>=2.0.0; extra == "datascience"
Provides-Extra: mcp
Requires-Dist: mcp>=1.0.0; extra == "mcp"
Provides-Extra: tools
Requires-Dist: noesium[aliyun,datascience,google,mcp]; extra == "tools"
Requires-Dist: wizsearch<2.0.0,>=1.0.1; extra == "tools"
Requires-Dist: arxiv>=2.2.0; extra == "tools"
Requires-Dist: pillow<12.0,>=10.1.0; extra == "tools"
Requires-Dist: pymupdf>=1.23.0; extra == "tools"
Requires-Dist: openpyxl>=3.1.5; extra == "tools"
Requires-Dist: wikipedia-api>=0.6.0; extra == "tools"
Provides-Extra: all
Requires-Dist: noesium[google,langchain,local-llm,openai,postgres,tools,weaviate]; extra == "all"
Provides-Extra: dev
Requires-Dist: pytest<9,>=8.2; extra == "dev"
Requires-Dist: pytest-cov>=4.0.0; extra == "dev"
Requires-Dist: pytest-asyncio>=1.1.0; extra == "dev"
Requires-Dist: black>=23.0.0; extra == "dev"
Requires-Dist: isort>=5.12.0; extra == "dev"
Requires-Dist: mypy>=1.10.0; extra == "dev"
Requires-Dist: autoflake>=2.3.1; extra == "dev"
Requires-Dist: flake8>=7.3.0; extra == "dev"
Dynamic: license-file
